<?xml version="1.0" encoding="utf-8" ?>
<dwsync>
<file name=".ptp-sync-folder" server="webprd2.uakron.edu//wwws/share/mailAllSource/" local="131916226066433702" remote="131916239190000000" Dst="1" />
<file name="angel_smile.gif" server="webprd2.uakron.edu//wwws/share/mailAllSource/" local="131916226066433702" remote="131916239190000000" Dst="1" />
<file name="angel_smile.png" server="webprd2.uakron.edu//wwws/share/mailAllSource/" local="131916226066433702" remote="131916239190000000" Dst="1" />
<file name="angry_smile.gif" server="webprd2.uakron.edu//wwws/share/mailAllSource/" local="131916226066443650" remote="131916239190000000" Dst="1" />
<file name="angry_smile.png" server="webprd2.uakron.edu//wwws/share/mailAllSource/" local="131916226066443650" remote="131916239200000000" Dst="1" />
<file name="broken_heart.gif" server="webprd2.uakron.edu//wwws/share/mailAllSource/" local="131916226066453620" remote="131916239200000000" Dst="1" />
<file name="broken_heart.png" server="webprd2.uakron.edu//wwws/share/mailAllSource/" local="131916226066453620" remote="131916239200000000" Dst="1" />
<file name="confused_smile.gif" server="webprd2.uakron.edu//wwws/share/mailAllSource/" local="131916226066453620" remote="131916239200000000" Dst="1" />
<file name="confused_smile.png" server="webprd2.uakron.edu//wwws/share/mailAllSource/" local="131916226066463594" remote="131916239200000000" Dst="1" />
<file name="cry_smile.gif" server="webprd2.uakron.edu//wwws/share/mailAllSource/" local="131916226066463594" remote="131916239200000000" Dst="1" />
<file name="cry_smile.png" server="webprd2.uakron.edu//wwws/share/mailAllSource/" local="131916226066473571" remote="131916239200000000" Dst="1" />
<file name="devil_smile.gif" server="webprd2.uakron.edu//wwws/share/mailAllSource/" local="131916226066473571" remote="131916239200000000" Dst="1" />
<file name="devil_smile.png" server="webprd2.uakron.edu//wwws/share/mailAllSource/" local="131916226066473571" remote="131916239200000000" Dst="1" />
<file name="embaressed_smile.gif" server="webprd2.uakron.edu//wwws/share/mailAllSource/" local="131916226066483542" remote="131916239200000000" Dst="1" />
<file name="embarrassed_smile.gif" server="webprd2.uakron.edu//wwws/share/mailAllSource/" local="131916226066483542" remote="131916239200000000" Dst="1" />
<file name="embarrassed_smile.png" server="webprd2.uakron.edu//wwws/share/mailAllSource/" local="131916226066493528" remote="131916239200000000" Dst="1" />
<file name="envelope.gif" server="webprd2.uakron.edu//wwws/share/mailAllSource/" local="131916226066493528" remote="131916239200000000" Dst="1" />
<file name="envelope.png" server="webprd2.uakron.edu//wwws/share/mailAllSource/" local="131916226066493528" remote="131916239210000000" Dst="1" />
<file name="heart.gif" server="webprd2.uakron.edu//wwws/share/mailAllSource/" local="131916226066503489" remote="131916239210000000" Dst="1" />
<file name="heart.png" server="webprd2.uakron.edu//wwws/share/mailAllSource/" local="131916226066503489" remote="131916239210000000" Dst="1" />
<file name="kiss.gif" server="webprd2.uakron.edu//wwws/share/mailAllSource/" local="131916226066513463" remote="131916239210000000" Dst="1" />
<file name="kiss.png" server="webprd2.uakron.edu//wwws/share/mailAllSource/" local="131916226066513463" remote="131916239210000000" Dst="1" />
<file name="lightbulb.gif" server="webprd2.uakron.edu//wwws/share/mailAllSource/" local="131916226066523427" remote="131916239210000000" Dst="1" />
<file name="lightbulb.png" server="webprd2.uakron.edu//wwws/share/mailAllSource/" local="131916226066523427" remote="131916239210000000" Dst="1" />
<file name="omg_smile.gif" server="webprd2.uakron.edu//wwws/share/mailAllSource/" local="131916226066523427" remote="131916239210000000" Dst="1" />
<file name="omg_smile.png" server="webprd2.uakron.edu//wwws/share/mailAllSource/" local="131916226066533410" remote="131916239210000000" Dst="1" />
<file name="regular_smile.gif" server="webprd2.uakron.edu//wwws/share/mailAllSource/" local="131916226066533410" remote="131916239210000000" Dst="1" />
<file name="regular_smile.png" server="webprd2.uakron.edu//wwws/share/mailAllSource/" local="131916226066533410" remote="131916239210000000" Dst="1" />
<file name="sad_smile.gif" server="webprd2.uakron.edu//wwws/share/mailAllSource/" local="131916226066543391" remote="131916239210000000" Dst="1" />
<file name="sad_smile.png" server="webprd2.uakron.edu//wwws/share/mailAllSource/" local="131916226066543391" remote="131916239210000000" Dst="1" />
<file name="shades_smile.gif" server="webprd2.uakron.edu//wwws/share/mailAllSource/" local="131916226066553358" remote="131916239210000000" Dst="1" />
<file name="shades_smile.png" server="webprd2.uakron.edu//wwws/share/mailAllSource/" local="131916226066553358" remote="131916239210000000" Dst="1" />
<file name="teeth_smile.gif" server="webprd2.uakron.edu//wwws/share/mailAllSource/" local="131916226066553358" remote="131916239220000000" Dst="1" />
<file name="teeth_smile.png" server="webprd2.uakron.edu//wwws/share/mailAllSource/" local="131916226066563325" remote="131916239220000000" Dst="1" />
<file name="thumbs_down.gif" server="webprd2.uakron.edu//wwws/share/mailAllSource/" local="131916226066563325" remote="131916239220000000" Dst="1" />
<file name="thumbs_down.png" server="webprd2.uakron.edu//wwws/share/mailAllSource/" local="131916226066573302" remote="131916239220000000" Dst="1" />
<file name="thumbs_up.gif" server="webprd2.uakron.edu//wwws/share/mailAllSource/" local="131916226066573302" remote="131916239220000000" Dst="1" />
<file name="thumbs_up.png" server="webprd2.uakron.edu//wwws/share/mailAllSource/" local="131916226066573302" remote="131916239220000000" Dst="1" />
<file name="tongue_smile.gif" server="webprd2.uakron.edu//wwws/share/mailAllSource/" local="131916226066583273" remote="131916239220000000" Dst="1" />
<file name="tongue_smile.png" server="webprd2.uakron.edu//wwws/share/mailAllSource/" local="131916226066583273" remote="131916239220000000" Dst="1" />
<file name="tounge_smile.gif" server="webprd2.uakron.edu//wwws/share/mailAllSource/" local="131916226066593246" remote="131916239220000000" Dst="1" />
<file name="whatchutalkingabout_smile.gif" server="webprd2.uakron.edu//wwws/share/mailAllSource/" local="131916226066593246" remote="131916239220000000" Dst="1" />
<file name="whatchutalkingabout_smile.png" server="webprd2.uakron.edu//wwws/share/mailAllSource/" local="131916226066593246" remote="131916239220000000" Dst="1" />
<file name="wink_smile.gif" server="webprd2.uakron.edu//wwws/share/mailAllSource/" local="131916226066603239" remote="131916239220000000" Dst="1" />
<file name="wink_smile.png" server="webprd2.uakron.edu//wwws/share/mailAllSource/" local="131916226066603239" remote="131916239220000000" Dst="1" />
</dwsync>